v36_2_setup.py
FUNCTIONS/__init__.py
FUNCTIONS/calculation.py
MiBetisCalculation.egg-info/PKG-INFO
MiBetisCalculation.egg-info/SOURCES.txt
MiBetisCalculation.egg-info/dependency_links.txt
MiBetisCalculation.egg-info/top_level.txt