Metadata-Version: 2.2
Name: MiBetisCalculation
Version: 1.0.0
Summary: Calculation Package
Author: Javier
Author-email: jprez@guidewire.com
Dynamic: author
Dynamic: author-email
Dynamic: summary
